yaml_keygen/__init__.py
yaml_keygen/keygen.py
yaml_keygen-0.1.8.dist-info/LICENSE
yaml_keygen-0.1.8.dist-info/METADATA
yaml_keygen-0.1.8.dist-info/WHEEL
yaml_keygen-0.1.8.dist-info/top_level.txt
yaml_keygen-0.1.8.dist-info/RECORD
