Metadata-Version: 2.1
Name: yaml-keygen
Version: 0.1.8
Summary: A Python module for extracting keys from a YAML file.
Home-page: https://github.com/fa1zali/yaml_keygen
Author: Faisal Ali
Author-email: fzl.ali33@gmail.com
License: MIT
Platform: UNKNOWN
Classifier: Intended Audience :: Developers
Classifier: License :: OSI Approved :: MIT License
Classifier: Programming Language :: Python
Classifier: Programming Language :: Python :: 3
Classifier: Programming Language :: Python :: 3.6
Classifier: Programming Language :: Python :: 3.7
Classifier: Programming Language :: Python :: 3.8
Classifier: Programming Language :: Python :: 3.9
Classifier: Programming Language :: Python :: 3.10
Classifier: Operating System :: OS Independent
License-File: LICENSE
Requires-Dist: ruamel.yaml
